README.md
setup.py
fresh9/ContextQA.py
fresh9/NoContextQA.py
fresh9/TextGen.py
fresh9/__init__.py
fresh9.egg-info/PKG-INFO
fresh9.egg-info/SOURCES.txt
fresh9.egg-info/dependency_links.txt
fresh9.egg-info/top_level.txt